<?xml version="1.0" encoding="utf-8"?>
<clothing-items>
 <clothing>
  <id>
   102321828
  </id>
  <name>
   Lacoste Skirt W-5213
  </name>
  <category>
   Skirt
  </category>
  <size>
   S
  </size>
  <color>
   Желтый
  </color>
  <material>
   Шерсть
  </material>
  <price>
   471693
  </price>
  <rating>
   2.08
  </rating>
  <reviews>
   145483
  </reviews>
  <new>
   -
  </new>
  <sporty>
   no
  </sporty>
 </clothing>
 <clothing>
  <id>
   689750930
  </id>
  <name>
   Adidas Socks F-8512
  </name>
  <category>
   Socks
  </category>
  <size>
   XXL
  </size>
  <color>
   Оранжевый
  </color>
  <material>
   Полиэстер
  </material>
  <price>
   440611
  </price>
  <rating>
   3.11
  </rating>
  <reviews>
   689808
  </reviews>
  <new>
   -
  </new>
  <exclusive>
   no
  </exclusive>
  <sporty>
   yes
  </sporty>
 </clothing>
 <clothing>
  <id>
   865108281
  </id>
  <name>
   Asics Umbrellas J-6000
  </name>
  <category>
   Umbrellas
  </category>
  <size>
   XXL
  </size>
  <color>
   Красный
  </color>
  <material>
   Полиэстер
  </material>
  <price>
   993746
  </price>
  <rating>
   4.21
  </rating>
  <reviews>
   808161
  </reviews>
  <new>
   +
  </new>
  <exclusive>
   no
  </exclusive>
 </clothing>
 <clothing>
  <id>
   708860842
  </id>
  <name>
   Under Armour Blouse X-5950
  </name>
  <category>
   Blouse
  </category>
  <size>
   M
  </size>
  <color>
   Оранжевый
  </color>
  <material>
   Шелк
  </material>
  <price>
   765443
  </price>
  <rating>
   3.68
  </rating>
  <reviews>
   320343
  </reviews>
  <sporty>
   no
  </sporty>
 </clothing>
 <clothing>
  <id>
   870554077
  </id>
  <name>
   Ellesse Jacket Q-4784
  </name>
  <category>
   Jacket
  </category>
  <size>
   XXL
  </size>
  <color>
   Голубой
  </color>
  <material>
   Хлопок
  </material>
  <price>
   984442
  </price>
  <rating>
   2.97
  </rating>
  <reviews>
   841980
  </reviews>
  <new>
   +
  </new>
  <exclusive>
   no
  </exclusive>
  <sporty>
   no
  </sporty>
 </clothing>
 <clothing>
  <id>
   961017118
  </id>
  <name>
   Converse Handbags H-1592
  </name>
  <category>
   Handbags
  </category>
  <size>
   XL
  </size>
  <color>
   Голубой
  </color>
  <material>
   Кожа
  </material>
  <price>
   152828
  </price>
  <rating>
   3.28
  </rating>
  <reviews>
   837561
  </reviews>
  <new>
   -
  </new>
  <exclusive>
   no
  </exclusive>
 </clothing>
 <clothing>
  <id>
   905051191
  </id>
  <name>
   Adidas Jeans H-1676
  </name>
  <category>
   Jeans
  </category>
  <size>
   XXL
  </size>
  <color>
   Голубой
  </color>
  <material>
   Шелк
  </material>
  <price>
   478485
  </price>
  <rating>
   4.82
  </rating>
  <reviews>
   552156
  </reviews>
  <new>
   +
  </new>
  <exclusive>
   no
  </exclusive>
  <sporty>
   yes
  </sporty>
 </clothing>
 <clothing>
  <id>
   514768644
  </id>
  <name>
   Addidas T-shirt O-8674
  </name>
  <category>
   T-shirt
  </category>
  <size>
   L
  </size>
  <color>
   Синий
  </color>
  <material>
   Полиэстер
  </material>
  <price>
   589651
  </price>
  <rating>
   2.73
  </rating>
  <reviews>
   725964
  </reviews>
  <new>
   +
  </new>
 </clothing>
 <clothing>
  <id>
   684859633
  </id>
  <name>
   Nike Sweater U-1793
  </name>
  <category>
   Sweater
  </category>
  <size>
   L
  </size>
  <color>
   Фиолетовый
  </color>
  <material>
   Шерсть
  </material>
  <price>
   364593
  </price>
  <rating>
   3.68
  </rating>
  <reviews>
   366865
  </reviews>
  <exclusive>
   no
  </exclusive>
 </clothing>
 <clothing>
  <id>
   668498389
  </id>
  <name>
   Addidas Belts V-8517
  </name>
  <category>
   Belts
  </category>
  <size>
   L
  </size>
  <color>
   Фиолетовый
  </color>
  <material>
   Лен
  </material>
  <price>
   247474
  </price>
  <rating>
   3.75
  </rating>
  <reviews>
   161959
  </reviews>
  <sporty>
   no
  </sporty>
 </clothing>
 <clothing>
  <id>
   588294086
  </id>
  <name>
   Brooks Hat X-6870
  </name>
  <category>
   Hat
  </category>
  <size>
   S
  </size>
  <color>
   Желтый
  </color>
  <material>
   Нейлон
  </material>
  <price>
   322244
  </price>
  <rating>
   3.51
  </rating>
  <reviews>
   459769
  </reviews>
  <new>
   -
  </new>
  <exclusive>
   no
  </exclusive>
  <sporty>
   no
  </sporty>
 </clothing>
 <clothing>
  <id>
   485824934
  </id>
  <name>
   New Balance Jeans Z-7315
  </name>
  <category>
   Jeans
  </category>
  <size>
   M
  </size>
  <color>
   Оранжевый
  </color>
  <material>
   Нейлон
  </material>
  <price>
   724588
  </price>
  <rating>
   2.55
  </rating>
  <reviews>
   287978
  </reviews>
 </clothing>
 <clothing>
  <id>
   610002729
  </id>
  <name>
   New Balance Sweater X-2762
  </name>
  <category>
   Sweater
  </category>
  <size>
   XL
  </size>
  <color>
   Оранжевый
  </color>
  <material>
   Шелк
  </material>
  <price>
   854644
  </price>
  <rating>
   1.92
  </rating>
  <reviews>
   539474
  </reviews>
  <exclusive>
   no
  </exclusive>
 </clothing>
 <clothing>
  <id>
   949360941
  </id>
  <name>
   Fila Pants P-2015
  </name>
  <category>
   Pants
  </category>
  <size>
   L
  </size>
  <color>
   Зеленый
  </color>
  <material>
   Шелк
  </material>
  <price>
   228750
  </price>
  <rating>
   1.69
  </rating>
  <reviews>
   827593
  </reviews>
  <sporty>
   no
  </sporty>
 </clothing>
 <clothing>
  <id>
   652599115
  </id>
  <name>
   Reebok T-shirt H-8822
  </name>
  <category>
   T-shirt
  </category>
  <size>
   M
  </size>
  <color>
   Оранжевый
  </color>
  <material>
   Шерсть
  </material>
  <price>
   401878
  </price>
  <rating>
   4.22
  </rating>
  <reviews>
   244110
  </reviews>
  <exclusive>
   no
  </exclusive>
 </clothing>
 <clothing>
  <id>
   811106023
  </id>
  <name>
   Asics Jacket N-4160
  </name>
  <category>
   Jacket
  </category>
  <size>
   L
  </size>
  <color>
   Желтый
  </color>
  <material>
   Полиэстер
  </material>
  <price>
   153529
  </price>
  <rating>
   1.23
  </rating>
  <reviews>
   342031
  </reviews>
  <new>
   -
  </new>
  <exclusive>
   yes
  </exclusive>
  <sporty>
   no
  </sporty>
 </clothing>
 <clothing>
  <id>
   547991123
  </id>
  <name>
   Vans Socks G-8050
  </name>
  <category>
   Socks
  </category>
  <size>
   M
  </size>
  <color>
   Синий
  </color>
  <material>
   Хлопок
  </material>
  <price>
   308763
  </price>
  <rating>
   1.57
  </rating>
  <reviews>
   368170
  </reviews>
  <new>
   +
  </new>
  <exclusive>
   no
  </exclusive>
 </clothing>
 <clothing>
  <id>
   377706610
  </id>
  <name>
   Reebok Jacket T-9404
  </name>
  <category>
   Jacket
  </category>
  <size>
   XXL
  </size>
  <color>
   Синий
  </color>
  <material>
   Шерсть
  </material>
  <price>
   229304
  </price>
  <rating>
   1.14
  </rating>
  <reviews>
   362370
  </reviews>
  <new>
   +
  </new>
  <exclusive>
   yes
  </exclusive>
 </clothing>
 <clothing>
  <id>
   807725432
  </id>
  <name>
   Asics Skirt J-5555
  </name>
  <category>
   Skirt
  </category>
  <size>
   XL
  </size>
  <color>
   Желтый
  </color>
  <material>
   Нейлон
  </material>
  <price>
   326230
  </price>
  <rating>
   1.06
  </rating>
  <reviews>
   58546
  </reviews>
 </clothing>
 <clothing>
  <id>
   184737677
  </id>
  <name>
   Asics Sweater P-8012
  </name>
  <category>
   Sweater
  </category>
  <size>
   XXL
  </size>
  <color>
   Красный
  </color>
  <material>
   Хлопок
  </material>
  <price>
   460963
  </price>
  <rating>
   4.11
  </rating>
  <reviews>
   560347
  </reviews>
  <new>
   -
  </new>
  <exclusive>
   no
  </exclusive>
  <sporty>
   no
  </sporty>
 </clothing>
 <clothing>
  <id>
   410902940
  </id>
  <name>
   Brooks Blouse W-1809
  </name>
  <category>
   Blouse
  </category>
  <size>
   S
  </size>
  <color>
   Красный
  </color>
  <material>
   Шерсть
  </material>
  <price>
   334220
  </price>
  <rating>
   3.76
  </rating>
  <reviews>
   98538
  </reviews>
  <exclusive>
   no
  </exclusive>
  <sporty>
   no
  </sporty>
 </clothing>
 <clothing>
  <id>
   283303035
  </id>
  <name>
   Fila Umbrellas Y-4777
  </name>
  <category>
   Umbrellas
  </category>
  <size>
   L
  </size>
  <color>
   Голубой
  </color>
  <material>
   Лен
  </material>
  <price>
   921666
  </price>
  <rating>
   4.4
  </rating>
  <reviews>
   562396
  </reviews>
  <new>
   +
  </new>
  <exclusive>
   no
  </exclusive>
 </clothing>
 <clothing>
  <id>
   956571612
  </id>
  <name>
   Nike Gloves I-2435
  </name>
  <category>
   Gloves
  </category>
  <size>
   XL
  </size>
  <color>
   Красный
  </color>
  <material>
   Кожа
  </material>
  <price>
   706955
  </price>
  <rating>
   1.49
  </rating>
  <reviews>
   513318
  </reviews>
  <new>
   -
  </new>
  <exclusive>
   yes
  </exclusive>
 </clothing>
 <clothing>
  <id>
   847935586
  </id>
  <name>
   Reebok Blouse D-3017
  </name>
  <category>
   Blouse
  </category>
  <size>
   XXL
  </size>
  <color>
   Синий
  </color>
  <material>
   Нейлон
  </material>
  <price>
   863386
  </price>
  <rating>
   1.86
  </rating>
  <reviews>
   951216
  </reviews>
  <exclusive>
   no
  </exclusive>
  <sporty>
   yes
  </sporty>
 </clothing>
 <clothing>
  <id>
   746344399
  </id>
  <name>
   PleinSport Gloves S-1907
  </name>
  <category>
   Gloves
  </category>
  <size>
   M
  </size>
  <color>
   Желтый
  </color>
  <material>
   Полиэстер
  </material>
  <price>
   450460
  </price>
  <rating>
   3.34
  </rating>
  <reviews>
   322293
  </reviews>
  <new>
   +
  </new>
  <exclusive>
   no
  </exclusive>
  <sporty>
   no
  </sporty>
 </clothing>
</clothing-items>
