<?xml version="1.0" encoding="utf-8"?>
<clothing-items>
 <clothing>
  <id>
   909188744
  </id>
  <name>
   Under Armour Shirt V-2164
  </name>
  <category>
   Shirt
  </category>
  <size>
   S
  </size>
  <color>
   Красный
  </color>
  <material>
   Вискоза
  </material>
  <price>
   354722
  </price>
  <rating>
   3.33
  </rating>
  <reviews>
   254023
  </reviews>
  <exclusive>
   yes
  </exclusive>
  <sporty>
   yes
  </sporty>
 </clothing>
 <clothing>
  <id>
   500202324
  </id>
  <name>
   Brooks Blouse S-2191
  </name>
  <category>
   Blouse
  </category>
  <size>
   L
  </size>
  <color>
   Фиолетовый
  </color>
  <material>
   Кожа
  </material>
  <price>
   126761
  </price>
  <rating>
   1.17
  </rating>
  <reviews>
   678400
  </reviews>
  <new>
   -
  </new>
  <exclusive>
   yes
  </exclusive>
  <sporty>
   no
  </sporty>
 </clothing>
 <clothing>
  <id>
   689629707
  </id>
  <name>
   Brooks Socks C-8429
  </name>
  <category>
   Socks
  </category>
  <size>
   XXL
  </size>
  <color>
   Красный
  </color>
  <material>
   Лен
  </material>
  <price>
   142541
  </price>
  <rating>
   1.96
  </rating>
  <reviews>
   939076
  </reviews>
  <new>
   -
  </new>
  <exclusive>
   yes
  </exclusive>
  <sporty>
   no
  </sporty>
 </clothing>
 <clothing>
  <id>
   646047304
  </id>
  <name>
   Asics Shoes R-5245
  </name>
  <category>
   Shoes
  </category>
  <size>
   L
  </size>
  <color>
   Желтый
  </color>
  <material>
   Хлопок
  </material>
  <price>
   987164
  </price>
  <rating>
   1.85
  </rating>
  <reviews>
   501166
  </reviews>
  <new>
   +
  </new>
  <exclusive>
   no
  </exclusive>
  <sporty>
   no
  </sporty>
 </clothing>
 <clothing>
  <id>
   100879037
  </id>
  <name>
   Asics Hat W-7582
  </name>
  <category>
   Hat
  </category>
  <size>
   S
  </size>
  <color>
   Оранжевый
  </color>
  <material>
   Хлопок
  </material>
  <price>
   197006
  </price>
  <rating>
   2.13
  </rating>
  <reviews>
   145029
  </reviews>
  <exclusive>
   no
  </exclusive>
 </clothing>
 <clothing>
  <id>
   529218985
  </id>
  <name>
   Brooks Shirt N-2746
  </name>
  <category>
   Shirt
  </category>
  <size>
   M
  </size>
  <color>
   Оранжевый
  </color>
  <material>
   Полиэстер
  </material>
  <price>
   352136
  </price>
  <rating>
   4.12
  </rating>
  <reviews>
   224464
  </reviews>
  <new>
   -
  </new>
  <exclusive>
   no
  </exclusive>
  <sporty>
   no
  </sporty>
 </clothing>
 <clothing>
  <id>
   328858617
  </id>
  <name>
   Lacoste Dress P-4436
  </name>
  <category>
   Dress
  </category>
  <size>
   M
  </size>
  <color>
   Красный
  </color>
  <material>
   Вискоза
  </material>
  <price>
   298623
  </price>
  <rating>
   1.71
  </rating>
  <reviews>
   859501
  </reviews>
 </clothing>
 <clothing>
  <id>
   883539538
  </id>
  <name>
   Under Armour Hat K-6847
  </name>
  <category>
   Hat
  </category>
  <size>
   L
  </size>
  <color>
   Зеленый
  </color>
  <material>
   Кожа
  </material>
  <price>
   697099
  </price>
  <rating>
   4.37
  </rating>
  <reviews>
   968374
  </reviews>
  <new>
   +
  </new>
  <exclusive>
   no
  </exclusive>
  <sporty>
   no
  </sporty>
 </clothing>
 <clothing>
  <id>
   383038988
  </id>
  <name>
   Asics Dress C-9353
  </name>
  <category>
   Dress
  </category>
  <size>
   XL
  </size>
  <color>
   Зеленый
  </color>
  <material>
   Нейлон
  </material>
  <price>
   167277
  </price>
  <rating>
   2.93
  </rating>
  <reviews>
   302094
  </reviews>
  <new>
   +
  </new>
  <exclusive>
   no
  </exclusive>
 </clothing>
 <clothing>
  <id>
   874949575
  </id>
  <name>
   Lacoste Belts L-7537
  </name>
  <category>
   Belts
  </category>
  <size>
   M
  </size>
  <color>
   Желтый
  </color>
  <material>
   Вискоза
  </material>
  <price>
   141685
  </price>
  <rating>
   1.06
  </rating>
  <reviews>
   935762
  </reviews>
  <new>
   -
  </new>
 </clothing>
 <clothing>
  <id>
   229134751
  </id>
  <name>
   Addidas Shoes O-2642
  </name>
  <category>
   Shoes
  </category>
  <size>
   XXL
  </size>
  <color>
   Фиолетовый
  </color>
  <material>
   Нейлон
  </material>
  <price>
   233721
  </price>
  <rating>
   3.48
  </rating>
  <reviews>
   203192
  </reviews>
  <exclusive>
   no
  </exclusive>
 </clothing>
 <clothing>
  <id>
   112009025
  </id>
  <name>
   PleinSport Jacket P-9555
  </name>
  <category>
   Jacket
  </category>
  <size>
   XXL
  </size>
  <color>
   Красный
  </color>
  <material>
   Полиэстер
  </material>
  <price>
   844440
  </price>
  <rating>
   1.04
  </rating>
  <reviews>
   55397
  </reviews>
  <new>
   -
  </new>
  <exclusive>
   no
  </exclusive>
 </clothing>
 <clothing>
  <id>
   834587337
  </id>
  <name>
   DC Blouse H-8829
  </name>
  <category>
   Blouse
  </category>
  <size>
   XL
  </size>
  <color>
   Зеленый
  </color>
  <material>
   Нейлон
  </material>
  <price>
   748085
  </price>
  <rating>
   3.23
  </rating>
  <reviews>
   266499
  </reviews>
  <new>
   -
  </new>
  <exclusive>
   yes
  </exclusive>
  <sporty>
   no
  </sporty>
 </clothing>
 <clothing>
  <id>
   766821712
  </id>
  <name>
   Ellesse Gloves Q-2630
  </name>
  <category>
   Gloves
  </category>
  <size>
   XL
  </size>
  <color>
   Оранжевый
  </color>
  <material>
   Шелк
  </material>
  <price>
   485766
  </price>
  <rating>
   1.66
  </rating>
  <reviews>
   23061
  </reviews>
 </clothing>
 <clothing>
  <id>
   462500795
  </id>
  <name>
   Under Armour Blouse B-2337
  </name>
  <category>
   Blouse
  </category>
  <size>
   XXL
  </size>
  <color>
   Синий
  </color>
  <material>
   Шелк
  </material>
  <price>
   762360
  </price>
  <rating>
   4.73
  </rating>
  <reviews>
   667033
  </reviews>
  <new>
   +
  </new>
  <exclusive>
   no
  </exclusive>
  <sporty>
   no
  </sporty>
 </clothing>
 <clothing>
  <id>
   249741361
  </id>
  <name>
   Brooks Shoes K-5774
  </name>
  <category>
   Shoes
  </category>
  <size>
   S
  </size>
  <color>
   Зеленый
  </color>
  <material>
   Шелк
  </material>
  <price>
   336366
  </price>
  <rating>
   1.25
  </rating>
  <reviews>
   164616
  </reviews>
  <sporty>
   no
  </sporty>
 </clothing>
 <clothing>
  <id>
   730719395
  </id>
  <name>
   PleinSport Umbrellas J-2827
  </name>
  <category>
   Umbrellas
  </category>
  <size>
   S
  </size>
  <color>
   Красный
  </color>
  <material>
   Кожа
  </material>
  <price>
   668468
  </price>
  <rating>
   3.4
  </rating>
  <reviews>
   495967
  </reviews>
  <new>
   +
  </new>
  <sporty>
   yes
  </sporty>
 </clothing>
 <clothing>
  <id>
   852890003
  </id>
  <name>
   PleinSport Socks B-6714
  </name>
  <category>
   Socks
  </category>
  <size>
   M
  </size>
  <color>
   Красный
  </color>
  <material>
   Хлопок
  </material>
  <price>
   814863
  </price>
  <rating>
   1.47
  </rating>
  <reviews>
   416937
  </reviews>
  <new>
   +
  </new>
  <sporty>
   yes
  </sporty>
 </clothing>
 <clothing>
  <id>
   245653732
  </id>
  <name>
   Lacoste Jacket S-4238
  </name>
  <category>
   Jacket
  </category>
  <size>
   XXL
  </size>
  <color>
   Красный
  </color>
  <material>
   Шелк
  </material>
  <price>
   803157
  </price>
  <rating>
   4.4
  </rating>
  <reviews>
   775159
  </reviews>
  <new>
   -
  </new>
  <exclusive>
   no
  </exclusive>
 </clothing>
 <clothing>
  <id>
   879110190
  </id>
  <name>
   Fila Hat A-5988
  </name>
  <category>
   Hat
  </category>
  <size>
   XXL
  </size>
  <color>
   Оранжевый
  </color>
  <material>
   Вискоза
  </material>
  <price>
   309906
  </price>
  <rating>
   4.63
  </rating>
  <reviews>
   539736
  </reviews>
  <new>
   -
  </new>
  <sporty>
   yes
  </sporty>
 </clothing>
 <clothing>
  <id>
   675926583
  </id>
  <name>
   Lacoste Socks F-3843
  </name>
  <category>
   Socks
  </category>
  <size>
   S
  </size>
  <color>
   Оранжевый
  </color>
  <material>
   Полиэстер
  </material>
  <price>
   809285
  </price>
  <rating>
   1.22
  </rating>
  <reviews>
   215798
  </reviews>
  <sporty>
   yes
  </sporty>
 </clothing>
 <clothing>
  <id>
   410371710
  </id>
  <name>
   Vans Shoes E-3705
  </name>
  <category>
   Shoes
  </category>
  <size>
   XXL
  </size>
  <color>
   Зеленый
  </color>
  <material>
   Полиэстер
  </material>
  <price>
   940200
  </price>
  <rating>
   4.93
  </rating>
  <reviews>
   615266
  </reviews>
  <exclusive>
   no
  </exclusive>
  <sporty>
   yes
  </sporty>
 </clothing>
 <clothing>
  <id>
   851689327
  </id>
  <name>
   Under Armour Shirt S-9240
  </name>
  <category>
   Shirt
  </category>
  <size>
   S
  </size>
  <color>
   Синий
  </color>
  <material>
   Хлопок
  </material>
  <price>
   956715
  </price>
  <rating>
   1.96
  </rating>
  <reviews>
   107643
  </reviews>
  <new>
   -
  </new>
  <sporty>
   yes
  </sporty>
 </clothing>
 <clothing>
  <id>
   702519491
  </id>
  <name>
   DC Shoes M-2084
  </name>
  <category>
   Shoes
  </category>
  <size>
   M
  </size>
  <color>
   Голубой
  </color>
  <material>
   Полиэстер
  </material>
  <price>
   106436
  </price>
  <rating>
   2.51
  </rating>
  <reviews>
   753109
  </reviews>
  <new>
   +
  </new>
 </clothing>
 <clothing>
  <id>
   470520566
  </id>
  <name>
   Under Armour Blouse A-8907
  </name>
  <category>
   Blouse
  </category>
  <size>
   L
  </size>
  <color>
   Фиолетовый
  </color>
  <material>
   Лен
  </material>
  <price>
   267099
  </price>
  <rating>
   3.96
  </rating>
  <reviews>
   163296
  </reviews>
  <exclusive>
   yes
  </exclusive>
  <sporty>
   no
  </sporty>
 </clothing>
 <clothing>
  <id>
   119499020
  </id>
  <name>
   New Balance Belts I-5696
  </name>
  <category>
   Belts
  </category>
  <size>
   XXL
  </size>
  <color>
   Фиолетовый
  </color>
  <material>
   Шерсть
  </material>
  <price>
   483776
  </price>
  <rating>
   1.38
  </rating>
  <reviews>
   391974
  </reviews>
  <new>
   -
  </new>
 </clothing>
 <clothing>
  <id>
   367592008
  </id>
  <name>
   Ellesse T-shirt N-2166
  </name>
  <category>
   T-shirt
  </category>
  <size>
   M
  </size>
  <color>
   Красный
  </color>
  <material>
   Вискоза
  </material>
  <price>
   765324
  </price>
  <rating>
   1.52
  </rating>
  <reviews>
   417690
  </reviews>
  <new>
   -
  </new>
  <exclusive>
   yes
  </exclusive>
 </clothing>
 <clothing>
  <id>
   305456641
  </id>
  <name>
   Ellesse Gloves D-9816
  </name>
  <category>
   Gloves
  </category>
  <size>
   S
  </size>
  <color>
   Желтый
  </color>
  <material>
   Шелк
  </material>
  <price>
   838999
  </price>
  <rating>
   3.06
  </rating>
  <reviews>
   526144
  </reviews>
  <new>
   -
  </new>
  <exclusive>
   no
  </exclusive>
 </clothing>
 <clothing>
  <id>
   645662441
  </id>
  <name>
   New Balance Jacket Y-1323
  </name>
  <category>
   Jacket
  </category>
  <size>
   L
  </size>
  <color>
   Зеленый
  </color>
  <material>
   Хлопок
  </material>
  <price>
   984536
  </price>
  <rating>
   2.72
  </rating>
  <reviews>
   180480
  </reviews>
  <sporty>
   no
  </sporty>
 </clothing>
 <clothing>
  <id>
   358983801
  </id>
  <name>
   Converse Blouse T-5774
  </name>
  <category>
   Blouse
  </category>
  <size>
   XXL
  </size>
  <color>
   Желтый
  </color>
  <material>
   Кожа
  </material>
  <price>
   672472
  </price>
  <rating>
   3.12
  </rating>
  <reviews>
   383938
  </reviews>
  <new>
   -
  </new>
  <exclusive>
   no
  </exclusive>
 </clothing>
 <clothing>
  <id>
   183868322
  </id>
  <name>
   Nike T-shirt S-9696
  </name>
  <category>
   T-shirt
  </category>
  <size>
   S
  </size>
  <color>
   Зеленый
  </color>
  <material>
   Кожа
  </material>
  <price>
   879880
  </price>
  <rating>
   4.52
  </rating>
  <reviews>
   404702
  </reviews>
  <new>
   -
  </new>
  <exclusive>
   no
  </exclusive>
  <sporty>
   no
  </sporty>
 </clothing>
 <clothing>
  <id>
   687106913
  </id>
  <name>
   Under Armour Sweater F-2087
  </name>
  <category>
   Sweater
  </category>
  <size>
   XL
  </size>
  <color>
   Красный
  </color>
  <material>
   Кожа
  </material>
  <price>
   964981
  </price>
  <rating>
   4.63
  </rating>
  <reviews>
   136029
  </reviews>
  <exclusive>
   no
  </exclusive>
 </clothing>
 <clothing>
  <id>
   733274679
  </id>
  <name>
   Brooks Blouse P-9800
  </name>
  <category>
   Blouse
  </category>
  <size>
   S
  </size>
  <color>
   Фиолетовый
  </color>
  <material>
   Нейлон
  </material>
  <price>
   268556
  </price>
  <rating>
   3.32
  </rating>
  <reviews>
   571299
  </reviews>
  <exclusive>
   no
  </exclusive>
  <sporty>
   no
  </sporty>
 </clothing>
 <clothing>
  <id>
   694115647
  </id>
  <name>
   PleinSport Belts T-1963
  </name>
  <category>
   Belts
  </category>
  <size>
   XXL
  </size>
  <color>
   Желтый
  </color>
  <material>
   Кожа
  </material>
  <price>
   392828
  </price>
  <rating>
   3.89
  </rating>
  <reviews>
   695872
  </reviews>
  <exclusive>
   yes
  </exclusive>
  <sporty>
   yes
  </sporty>
 </clothing>
 <clothing>
  <id>
   443718998
  </id>
  <name>
   Puma Blouse M-9608
  </name>
  <category>
   Blouse
  </category>
  <size>
   XL
  </size>
  <color>
   Зеленый
  </color>
  <material>
   Шелк
  </material>
  <price>
   195424
  </price>
  <rating>
   1.12
  </rating>
  <reviews>
   697068
  </reviews>
  <new>
   +
  </new>
  <exclusive>
   yes
  </exclusive>
  <sporty>
   yes
  </sporty>
 </clothing>
 <clothing>
  <id>
   486974421
  </id>
  <name>
   Under Armour Hat B-2046
  </name>
  <category>
   Hat
  </category>
  <size>
   S
  </size>
  <color>
   Зеленый
  </color>
  <material>
   Кожа
  </material>
  <price>
   202265
  </price>
  <rating>
   2.4
  </rating>
  <reviews>
   164303
  </reviews>
  <new>
   +
  </new>
  <exclusive>
   no
  </exclusive>
  <sporty>
   yes
  </sporty>
 </clothing>
 <clothing>
  <id>
   670429403
  </id>
  <name>
   Lacoste Belts E-4018
  </name>
  <category>
   Belts
  </category>
  <size>
   S
  </size>
  <color>
   Фиолетовый
  </color>
  <material>
   Нейлон
  </material>
  <price>
   429114
  </price>
  <rating>
   1.78
  </rating>
  <reviews>
   878649
  </reviews>
  <new>
   -
  </new>
  <exclusive>
   yes
  </exclusive>
 </clothing>
 <clothing>
  <id>
   666595201
  </id>
  <name>
   Brooks Sweater P-6724
  </name>
  <category>
   Sweater
  </category>
  <size>
   XXL
  </size>
  <color>
   Желтый
  </color>
  <material>
   Хлопок
  </material>
  <price>
   998660
  </price>
  <rating>
   2.14
  </rating>
  <reviews>
   557910
  </reviews>
 </clothing>
 <clothing>
  <id>
   911318032
  </id>
  <name>
   Puma Hat J-1557
  </name>
  <category>
   Hat
  </category>
  <size>
   XL
  </size>
  <color>
   Желтый
  </color>
  <material>
   Полиэстер
  </material>
  <price>
   348520
  </price>
  <rating>
   3.36
  </rating>
  <reviews>
   32173
  </reviews>
  <new>
   -
  </new>
  <sporty>
   no
  </sporty>
 </clothing>
 <clothing>
  <id>
   362837714
  </id>
  <name>
   Fila Socks F-6621
  </name>
  <category>
   Socks
  </category>
  <size>
   XXL
  </size>
  <color>
   Синий
  </color>
  <material>
   Шерсть
  </material>
  <price>
   677830
  </price>
  <rating>
   1.82
  </rating>
  <reviews>
   789414
  </reviews>
  <new>
   -
  </new>
  <exclusive>
   no
  </exclusive>
  <sporty>
   no
  </sporty>
 </clothing>
 <clothing>
  <id>
   499117669
  </id>
  <name>
   Lacoste Handbags J-9049
  </name>
  <category>
   Handbags
  </category>
  <size>
   M
  </size>
  <color>
   Зеленый
  </color>
  <material>
   Шелк
  </material>
  <price>
   414157
  </price>
  <rating>
   1.5
  </rating>
  <reviews>
   654434
  </reviews>
  <new>
   +
  </new>
  <exclusive>
   no
  </exclusive>
  <sporty>
   yes
  </sporty>
 </clothing>
 <clothing>
  <id>
   631103936
  </id>
  <name>
   PleinSport Gloves D-6120
  </name>
  <category>
   Gloves
  </category>
  <size>
   L
  </size>
  <color>
   Желтый
  </color>
  <material>
   Шелк
  </material>
  <price>
   176556
  </price>
  <rating>
   1.99
  </rating>
  <reviews>
   535042
  </reviews>
  <new>
   -
  </new>
  <exclusive>
   no
  </exclusive>
  <sporty>
   no
  </sporty>
 </clothing>
 <clothing>
  <id>
   826417216
  </id>
  <name>
   PleinSport Blouse R-4520
  </name>
  <category>
   Blouse
  </category>
  <size>
   S
  </size>
  <color>
   Фиолетовый
  </color>
  <material>
   Хлопок
  </material>
  <price>
   225255
  </price>
  <rating>
   1.42
  </rating>
  <reviews>
   507091
  </reviews>
  <new>
   -
  </new>
  <exclusive>
   yes
  </exclusive>
  <sporty>
   yes
  </sporty>
 </clothing>
 <clothing>
  <id>
   331531300
  </id>
  <name>
   Fila Socks R-7517
  </name>
  <category>
   Socks
  </category>
  <size>
   M
  </size>
  <color>
   Синий
  </color>
  <material>
   Полиэстер
  </material>
  <price>
   813692
  </price>
  <rating>
   2.63
  </rating>
  <reviews>
   510475
  </reviews>
 </clothing>
 <clothing>
  <id>
   118389604
  </id>
  <name>
   Lacoste Dress M-6013
  </name>
  <category>
   Dress
  </category>
  <size>
   M
  </size>
  <color>
   Красный
  </color>
  <material>
   Шелк
  </material>
  <price>
   120517
  </price>
  <rating>
   4.71
  </rating>
  <reviews>
   488079
  </reviews>
  <new>
   -
  </new>
  <sporty>
   yes
  </sporty>
 </clothing>
 <clothing>
  <id>
   938341168
  </id>
  <name>
   Asics Shoes R-8569
  </name>
  <category>
   Shoes
  </category>
  <size>
   L
  </size>
  <color>
   Фиолетовый
  </color>
  <material>
   Нейлон
  </material>
  <price>
   458814
  </price>
  <rating>
   1.0
  </rating>
  <reviews>
   508394
  </reviews>
  <sporty>
   no
  </sporty>
 </clothing>
 <clothing>
  <id>
   193668498
  </id>
  <name>
   PleinSport Dress N-8614
  </name>
  <category>
   Dress
  </category>
  <size>
   XXL
  </size>
  <color>
   Голубой
  </color>
  <material>
   Нейлон
  </material>
  <price>
   362711
  </price>
  <rating>
   2.06
  </rating>
  <reviews>
   298165
  </reviews>
  <sporty>
   no
  </sporty>
 </clothing>
 <clothing>
  <id>
   799314265
  </id>
  <name>
   Under Armour Belts J-6180
  </name>
  <category>
   Belts
  </category>
  <size>
   L
  </size>
  <color>
   Синий
  </color>
  <material>
   Полиэстер
  </material>
  <price>
   894054
  </price>
  <rating>
   4.84
  </rating>
  <reviews>
   740706
  </reviews>
  <new>
   +
  </new>
  <exclusive>
   no
  </exclusive>
  <sporty>
   no
  </sporty>
 </clothing>
 <clothing>
  <id>
   956091932
  </id>
  <name>
   Fila Belts B-2696
  </name>
  <category>
   Belts
  </category>
  <size>
   XXL
  </size>
  <color>
   Красный
  </color>
  <material>
   Кожа
  </material>
  <price>
   107758
  </price>
  <rating>
   3.71
  </rating>
  <reviews>
   603201
  </reviews>
  <new>
   +
  </new>
  <exclusive>
   yes
  </exclusive>
  <sporty>
   no
  </sporty>
 </clothing>
</clothing-items>
